{
  "artist": [
    {
      "id": 0,
      "firstName": "Cecilia",
      "lastName": "Paschall",
      "picture": "https://picsum.photos/seed/artist0/200/200"
    }
    ,
    {
      "id": 1,
      "firstName": "Rikki",
      "lastName": "Jensen",
      "picture": "https://picsum.photos/seed/artist1/200/200"
    }
    ,
    {
      "id": 2,
      "firstName": "Elaine",
      "lastName": "Bourquin",
      "picture": "https://picsum.photos/seed/artist2/200/200"
    }
    ,
    {
      "id": 3,
      "firstName": "Theo",
      "lastName": "Paquette",
      "picture": "https://picsum.photos/seed/artist3/200/200"
    }
    ,
    {
      "id": 4,
      "firstName": "Raylene",
      "lastName": "Hottle",
      "picture": "https://picsum.photos/seed/artist4/200/200"
    }
    ,
    {
      "id": 5,
      "firstName": "Liza",
      "lastName": "White",
      "picture": "https://picsum.photos/seed/artist5/200/200"
    }
    ,
    {
      "id": 6,
      "firstName": "Victoria",
      "lastName": "Remus",
      "picture": "https://picsum.photos/seed/artist6/200/200"
    }
    ,
    {
      "id": 7,
      "firstName": "Richelle",
      "lastName": "Latshaw",
      "picture": "https://picsum.photos/seed/artist7/200/200"
    }
    ,
    {
      "id": 8,
      "firstName": "Lance",
      "lastName": "Garling",
      "picture": "https://picsum.photos/seed/artist8/200/200"
    }
    ,
    {
      "id": 9,
      "firstName": "Rosanne",
      "lastName": "Keesee",
      "picture": "https://picsum.photos/seed/artist9/200/200"
    }
  ],

  "music": [
    {
      "id": 0,
      "title": "Facilisis pharetra.",
      "artist": 4,
      "album": 2,
      "picture": "https://picsum.photos/seed/music91645/200/200",
      "type": "Electro",
      "publication": "2018-09-14",
      "audio": "/audio/mixkit-hip-hop-02-738.mp3"
    }
    ,
    {
      "id": 1,
      "title": "Sit pulvinar.",
      "artist": 5,
      "album": 3,
      "picture": "https://picsum.photos/seed/music51915/200/200",
      "type": "Rock",
      "publication": "2022-12-10",
      "audio": "/audio/mixkit-sun-and-his-daughter-580.mp3"
    }
    ,
    {
      "id": 2,
      "title": "Quisque non lorem.",
      "artist": 8,
      "album": 1,
      "picture": "https://picsum.photos/seed/music50918/200/200",
      "type": "Pop",
      "publication": "2016-12-29",
      "audio": "/audio/mixkit-tech-house-vibes-130.mp3"
    }
    ,
    {
      "id": 3,
      "title": "Mattis ex sodales.",
      "artist": 2,
      "album": 2,
      "picture": "https://picsum.photos/seed/music70752/200/200",
      "type": "Pop",
      "publication": "2012-07-16",
      "audio": "/audio/mixkit-a-very-happy-christmas-897.mp3"
    }
    ,
    {
      "id": 4,
      "title": "Commodo mi.",
      "artist": 6,
      "album": 4,
      "picture": "https://picsum.photos/seed/music94787/200/200",
      "type": "Electro",
      "publication": "2013-08-03",
      "audio": "/audio/mixkit-beautiful-dream-493.mp3"
    }
    ,
    {
      "id": 5,
      "title": "Tortor con ligula.",
      "artist": 9,
      "album": 2,
      "picture": "https://picsum.photos/seed/music47909/200/200",
      "type": "Rock",
      "publication": "2016-01-15",
      "audio": "/audio/mixkit-deep-urban-623.mp3"
    }
    ,
    {
      "id": 6,
      "title": "El pulvinar dia.",
      "artist": 9,
      "album": 0,
      "picture": "https://picsum.photos/seed/music92643/200/200",
      "type": "Alternative",
      "publication": "2019-05-04",
      "audio": "/audio/mixkit-beautiful-dream-493.mp3"
    }
    ,
    {
      "id": 7,
      "title": "Sollicitudin neque.",
      "artist": 1,
      "album": 0,
      "picture": "https://picsum.photos/seed/music90526/200/200",
      "type": "Electro",
      "publication": "2011-06-22",
      "audio": "/audio/mixkit-deep-urban-623.mp3"
    }
    ,
    {
      "id": 8,
      "title": "Fringilla it.",
      "artist": 2,
      "album": 2,
      "picture": "https://picsum.photos/seed/music88209/200/200",
      "type": "Alternative",
      "publication": "2011-06-23",
      "audio": "/audio/mixkit-driving-ambition-32.mp3"
    }
    ,
    {
      "id": 9,
      "title": "Aliquet nulla imperdiet.",
      "artist": 1,
      "album": 1,
      "picture": "https://picsum.photos/seed/music71304/200/200",
      "type": "Rap",
      "publication": "2014-11-11",
      "audio": "/audio/mixkit-hip-hop-02-738.mp3"
    }
    ,
    {
      "id": 10,
      "title": "Proin lacinia.",
      "artist": 4,
      "album": 1,
      "picture": "https://picsum.photos/seed/music45563/200/200",
      "type": "Rap",
      "publication": "2021-08-15",
      "audio": "/audio/mixkit-sun-and-his-daughter-580.mp3"
    }
    ,
    {
      "id": 11,
      "title": "Et suscipit dictum.",
      "artist": 6,
      "album": 2,
      "picture": "https://picsum.photos/seed/music53711/200/200",
      "type": "Rap",
      "publication": "2018-12-15",
      "audio": "/audio/mixkit-driving-ambition-32.mp3"
    }
    ,
    {
      "id": 12,
      "title": "Lacus non.",
      "artist": 3,
      "album": 4,
      "picture": "https://picsum.photos/seed/music20175/200/200",
      "type": "Rock",
      "publication": "2015-09-19",
      "audio": "/audio/mixkit-deep-urban-623.mp3"
    }
    ,
    {
      "id": 13,
      "title": "Neque enim.",
      "artist": 2,
      "album": 4,
      "picture": "https://picsum.photos/seed/music81694/200/200",
      "type": "Classic",
      "publication": "2014-06-10",
      "audio": "/audio/mixkit-a-very-happy-christmas-897.mp3"
    }
    ,
    {
      "id": 14,
      "title": "Lacus cras i.",
      "artist": 2,
      "album": 2,
      "picture": "https://picsum.photos/seed/music70643/200/200",
      "type": "Rap",
      "publication": "2015-11-04",
      "audio": "/audio/mixkit-driving-ambition-32.mp3"
    }
    ,
    {
      "id": 15,
      "title": "Mi ac.",
      "artist": 6,
      "album": 3,
      "picture": "https://picsum.photos/seed/music98727/200/200",
      "type": "Rap",
      "publication": "2012-05-03",
      "audio": "/audio/mixkit-sun-and-his-daughter-580.mp3"
    }
    ,
    {
      "id": 16,
      "title": "Ornare gravida.",
      "artist": 2,
      "album": 4,
      "picture": "https://picsum.photos/seed/music30781/200/200",
      "type": "Pop",
      "publication": "2022-01-17",
      "audio": "/audio/mixkit-hip-hop-02-738.mp3"
    }
    ,
    {
      "id": 17,
      "title": "Velit pulvinar.",
      "artist": 9,
      "album": 1,
      "picture": "https://picsum.photos/seed/music97486/200/200",
      "type": "Classic",
      "publication": "2018-08-16",
      "audio": "/audio/mixkit-hip-hop-02-738.mp3"
    }
    ,
    {
      "id": 18,
      "title": "En elit ac.",
      "artist": 6,
      "album": 3,
      "picture": "https://picsum.photos/seed/music72568/200/200",
      "type": "Rap",
      "publication": "2011-02-01",
      "audio": "/audio/mixkit-a-very-happy-christmas-897.mp3"
    }
    ,
    {
      "id": 19,
      "title": "Suscipit etiam felis.",
      "artist": 0,
      "album": 3,
      "picture": "https://picsum.photos/seed/music13379/200/200",
      "type": "Pop",
      "publication": "2024-07-16",
      "audio": "/audio/mixkit-sun-and-his-daughter-580.mp3"
    }
  ],

  "list": [
    {
      "id": 0,
      "title": "Cursus gravida ut.",
      "artist": 0,
      "picture": "https://picsum.photos/seed/list0/300/300",
      "type": "album",
      "publication": "2023-05-28",
      "musics": [
          14,
          15,
          7,
          1,
          18
      ]
    }
    ,
    {
      "id": 1,
      "title": "Non magna.",
      "artist": 2,
      "picture": "https://picsum.photos/seed/list1/300/300",
      "type": "playlist",
      "publication": "2010-11-19",
      "musics": [
          0,
          8,
          3,
          5,
          0,
          12,
          14
      ]
    }
    ,
    {
      "id": 2,
      "title": "Mi lacinia.",
      "artist": 9,
      "picture": "https://picsum.photos/seed/list2/300/300",
      "type": "playlist",
      "publication": "2013-08-03",
      "musics": [
          9,
          12,
          10,
          4,
          10
      ]
    }
    ,
    {
      "id": 3,
      "title": "Aenean elit.",
      "artist": 5,
      "picture": "https://picsum.photos/seed/list3/300/300",
      "type": "album",
      "publication": "2022-07-29",
      "musics": [
          13,
          18,
          17,
          9,
          14,
          11,
          9
      ]
    }
    ,
    {
      "id": 4,
      "title": "Elit dolor nulla.",
      "artist": 4,
      "picture": "https://picsum.photos/seed/list4/300/300",
      "type": "playlist",
      "publication": "2012-08-03",
      "musics": [
          13,
          2,
          7,
          16,
          15,
          8
      ]
    }
  ]
}

